README.rst
setup.py
directories/__init__.py
directories/directories_class.py
directories.egg-info/PKG-INFO
directories.egg-info/SOURCES.txt
directories.egg-info/dependency_links.txt
directories.egg-info/requires.txt
directories.egg-info/top_level.txt