Metadata-Version: 1.2
Name: directories
Version: 1.0.1
Summary: This is a class that helps make dealing with your scripts directories easier
Home-page: https://github.com/btr1975/directories
Author: Benjamin P. Trachtenberg
Author-email: e_ben_75-python@yahoo.com
License: MIT
Keywords: dir class directories yml
Platform: UNKNOWN
Classifier: Development Status :: 5 - Production/Stable
Classifier: Intended Audience :: Developers
Classifier: License :: OSI Approved :: MIT License
Classifier: Programming Language :: Python :: 3
Requires-Python: ~=3.5
